Flask_Materialize-0.2.4.dist-info/METADATA
Flask_Materialize-0.2.4.dist-info/RECORD
Flask_Materialize-0.2.4.dist-info/WHEEL
Flask_Materialize-0.2.4.dist-info/top_level.txt
flask_material/__init__.py
flask_material/static/css/materialize.css
flask_material/static/css/materialize.min.css
flask_material/static/font/material-design-icons/LICENSE.txt
flask_material/static/font/material-design-icons/Material-Design-Icons.eot
flask_material/static/font/material-design-icons/Material-Design-Icons.svg
flask_material/static/font/material-design-icons/Material-Design-Icons.ttf
flask_material/static/font/material-design-icons/Material-Design-Icons.woff
flask_material/static/font/material-design-icons/Material-Design-Icons.woff2
flask_material/static/font/roboto/Roboto-Bold.ttf
flask_material/static/font/roboto/Roboto-Bold.woff
flask_material/static/font/roboto/Roboto-Bold.woff2
flask_material/static/font/roboto/Roboto-Light.ttf
flask_material/static/font/roboto/Roboto-Light.woff
flask_material/static/font/roboto/Roboto-Light.woff2
flask_material/static/font/roboto/Roboto-Medium.ttf
flask_material/static/font/roboto/Roboto-Medium.woff
flask_material/static/font/roboto/Roboto-Medium.woff2
flask_material/static/font/roboto/Roboto-Regular.ttf
flask_material/static/font/roboto/Roboto-Regular.woff
flask_material/static/font/roboto/Roboto-Regular.woff2
flask_material/static/font/roboto/Roboto-Thin.ttf
flask_material/static/font/roboto/Roboto-Thin.woff
flask_material/static/font/roboto/Roboto-Thin.woff2
flask_material/static/js/html5shiv.min.js
flask_material/static/js/jquery.js
flask_material/static/js/jquery.min.js
flask_material/static/js/materialize.js
flask_material/static/js/materialize.min.js
flask_material/static/js/respond.min.js
flask_material/templates/material/base.html
flask_material/templates/material/fixes.html
flask_material/templates/material/google.html
flask_material/templates/material/pagination.html
flask_material/templates/material/rowscols.html
flask_material/templates/material/utils.html
flask_material/templates/material/wtf.html
flask_materialize/__init__.py
