Metadata-Version: 1.1
Name: Flask-Materialize
Version: 0.2.4
Summary: An extension that includes Materialize CSS (http://materializecss.com/) in your project, without any boilerplate code.
Home-page: https://bitbucket.org/cyberspy/flask_materialize
Author: Adam Cadman
Author-email: cyberspy.oss@gmx.com
License: MIT
Keywords: flask materialize materializecss material design css html layout bootstrap responsive widgets wtforms templates
Platform: any
Classifier: Environment :: Web Environment
Classifier: Intended Audience :: Developers
Classifier: License :: OSI Approved :: MIT License
Classifier: Operating System :: OS Independent
Classifier: Framework :: Flask
Classifier: Development Status :: 5 - Production/Stable
Classifier: Programming Language :: Python
Classifier: Programming Language :: Python :: 2.7
Classifier: Programming Language :: Python :: 3
Classifier: Topic :: Internet :: WWW/HTTP :: Dynamic Content
Classifier: Topic :: Software Development :: Libraries :: Python Modules
Classifier: Topic :: Software Development :: User Interfaces
